psdi_data_conversion/__init__.py
psdi_data_conversion/app.py
psdi_data_conversion/constants.py
psdi_data_conversion/converter.py
psdi_data_conversion/database.py
psdi_data_conversion/dist.py
psdi_data_conversion/file_io.py
psdi_data_conversion/log_utility.py
psdi_data_conversion/main.py
psdi_data_conversion/main_gui.py
psdi_data_conversion/security.py
psdi_data_conversion/utils.py
psdi_data_conversion/bin/LICENSE_ATOMSK
psdi_data_conversion/bin/LICENSE_C2X
psdi_data_conversion/bin/linux/atomsk
psdi_data_conversion/bin/linux/c2x
psdi_data_conversion/bin/mac/atomsk
psdi_data_conversion/bin/mac/c2x
psdi_data_conversion/converters/__init__.py
psdi_data_conversion/converters/atomsk.py
psdi_data_conversion/converters/base.py
psdi_data_conversion/converters/c2x.py
psdi_data_conversion/converters/openbabel.py
psdi_data_conversion/gui/__init__.py
psdi_data_conversion/gui/accessibility.py
psdi_data_conversion/gui/authentication.py
psdi_data_conversion/gui/env.py
psdi_data_conversion/gui/get.py
psdi_data_conversion/gui/post.py
psdi_data_conversion/gui/setup.py
psdi_data_conversion/scripts/atomsk.sh
psdi_data_conversion/scripts/c2x.sh
psdi_data_conversion/static/data/data.json
psdi_data_conversion/static/img/colormode-toggle-dm.svg
psdi_data_conversion/static/img/colormode-toggle-lm.svg
psdi_data_conversion/static/img/psdi-icon-dark.svg
psdi_data_conversion/static/img/psdi-icon-light.svg
psdi_data_conversion/static/img/psdi-logo-darktext-simple.png
psdi_data_conversion/static/img/psdi-logo-darktext.png
psdi_data_conversion/static/img/psdi-logo-lighttext-simple.png
psdi_data_conversion/static/img/psdi-logo-lighttext.png
psdi_data_conversion/static/img/social-logo-bluesky-black.svg
psdi_data_conversion/static/img/social-logo-bluesky-white.svg
psdi_data_conversion/static/img/social-logo-instagram-black.svg
psdi_data_conversion/static/img/social-logo-instagram-white.svg
psdi_data_conversion/static/img/social-logo-linkedin-black.png
psdi_data_conversion-0.3.18.dist-info/METADATA
psdi_data_conversion-0.3.18.dist-info/WHEEL
psdi_data_conversion-0.3.18.dist-info/entry_points.txt
psdi_data_conversion-0.3.18.dist-info/licenses/LICENSE
psdi_data_conversion-0.3.18.dist-info/RECORD
