Metadata-Version: 2.4
Name: psdi_data_conversion
Version: 0.3.18
Summary: Chemistry file format conversion service, provided by PSDI
Project-URL: Homepage, https://data-conversion.psdi.ac.uk/
Project-URL: Documentation, https://psdi-uk.github.io/psdi-data-conversion/
Project-URL: Issues, https://github.com/PSDI-UK/psdi-data-conversion/issues
Project-URL: Changelog, https://github.com/PSDI-UK/psdi-data-conversion/blob/main/CHANGELOG.md
Project-URL: Repository, https://github.com/PSDI-UK/psdi-data-conversion
Project-URL: Download, https://github.com/PSDI-UK/psdi-data-conversion/releases/latest
Author: Ray Whorley, Don Cruickshank, Tom Underwood
Author-email: Samantha Pearman-Kanza <s.pearman-kanza@soton.ac.uk>, Bryan Gillis <7204836+brgillis@users.noreply.github.com>
License:                                  Apache License
License-File: LICENSE
Keywords: atomsk,chemistry,conversion,flask,openbabel
Classifier: Development Status :: 3 - Alpha
Classifier: Framework :: Flask
Classifier: Intended Audience :: Science/Research
Classifier: License :: OSI Approved :: Apache Software License
Classifier: Natural Language :: English
Classifier: Operating System :: POSIX :: Linux
Classifier: Programming Language :: JavaScript
Classifier: Programming Language :: Python :: 3
Classifier: Topic :: File Formats
Classifier: Topic :: Scientific/Engineering :: Chemistry
Requires-Python: >=3.11
Requires-Dist: igraph
Requires-Dist: openbabel-wheel
Requires-Dist: py
Provides-Extra: deploy
Requires-Dist: cachetools; extra == 'deploy'
Requires-Dist: flask; extra == 'deploy'
Requires-Dist: gunicorn; extra == 'deploy'
Requires-Dist: pyjwt[crypto]; extra == 'deploy'
Requires-Dist: requests; extra == 'deploy'
Provides-Extra: doc
Requires-Dist: cachetools; extra == 'doc'
Requires-Dist: flask; extra == 'doc'
Requires-Dist: gunicorn; extra == 'doc'
Requires-Dist: pdoc3; extra == 'doc'
Requires-Dist: pyjwt[crypto]; extra == 'doc'
Requires-Dist: pytest; extra == 'doc'
Requires-Dist: requests; extra == 'doc'
Requires-Dist: selenium; extra == 'doc'
Provides-Extra: gui
Requires-Dist: flask; extra == 'gui'
Requires-Dist: requests; extra == 'gui'
Provides-Extra: gui-test
Requires-Dist: coverage; extra == 'gui-test'
Requires-Dist: flask; extra == 'gui-test'
Requires-Dist: pytest; extra == 'gui-test'
Requires-Dist: requests; extra == 'gui-test'
Requires-Dist: selenium; extra == 'gui-test'
Requires-Dist: webdriver-manager; extra == 'gui-test'
Provides-Extra: plots
Requires-Dist: matplotlib; extra == 'plots'
Provides-Extra: test
Requires-Dist: coverage; extra == 'test'
Requires-Dist: pytest; extra == 'test'
